shbus/__init__.py
shbus/consts.py
shbus/lineinfo.py
shbus/models.py
shbus/realtime.py
shbus/utils.py
shbus/protos/NameSet_pb2.py
shbus/protos/Request_pb2.py
shbus/protos/Response_pb2.py
shbus/protos/__init__.py
shbus-2.0.0.dist-info/LICENSE
shbus-2.0.0.dist-info/METADATA
shbus-2.0.0.dist-info/WHEEL
shbus-2.0.0.dist-info/top_level.txt
shbus-2.0.0.dist-info/RECORD
