Metadata-Version: 2.1
Name: shbus
Version: 2.0.0
Summary: Python implementation of Shanghai Bus App.
Home-page: https://github.com/hebingchang/shanghai-realtime-bus
Author: hebingchang
Author-email: hebingchang1@live.com
License: MIT Licence
Keywords: pip,shanghai,realtime,bus
Platform: any
License-File: LICENSE
Requires-Dist: requests
Requires-Dist: pycryptodome
Requires-Dist: protobuf
